mseep_pyserini-1.2.4.dist-info/licenses/LICENSE.txt
pyserini/__init__.py
pyserini/encoded_corpus_info.py
pyserini/encoded_query_info.py
pyserini/evaluate_script_info.py
pyserini/external_query_info.py
pyserini/multithreading.py
pyserini/output_writer.py
pyserini/prebuilt_index_info.py
pyserini/pyclass.py
pyserini/query_iterator.py
pyserini/query_iterator_order_info.py
pyserini/setup.py
pyserini/tokenize_json_collection.py
pyserini/util.py
pyserini/2cr/__init__.py
pyserini/2cr/_base.py
pyserini/2cr/atomic.py
pyserini/2cr/atomic.yaml
pyserini/2cr/atomic_html.template
pyserini/2cr/atomic_html_row.template
pyserini/2cr/beir.py
pyserini/2cr/beir.yaml
pyserini/2cr/beir_html.template
pyserini/2cr/beir_html_row.template
pyserini/2cr/ciral.py
pyserini/2cr/ciral.yaml
pyserini/2cr/ciral_html.template
pyserini/2cr/ciral_html_table.template
pyserini/2cr/ciral_html_table_row.template
pyserini/2cr/miracl.py
pyserini/2cr/miracl.yaml
pyserini/2cr/miracl_html.template
pyserini/2cr/miracl_html_table.template
pyserini/2cr/miracl_html_table_row.template
pyserini/2cr/mrtydi.py
pyserini/2cr/mrtydi.yaml
pyserini/2cr/mrtydi_html.template
pyserini/2cr/mrtydi_html_table.template
pyserini/2cr/mrtydi_html_table_row.template
pyserini/2cr/msmarco-v1-doc.yaml
pyserini/2cr/msmarco-v1-passage.yaml
pyserini/2cr/msmarco-v2-doc.yaml
pyserini/2cr/msmarco-v2-passage.yaml
pyserini/2cr/msmarco.py
pyserini/2cr/msmarco_html_row_v1.template
pyserini/2cr/msmarco_html_row_v2.template
pyserini/2cr/msmarco_html_v1_doc.template
pyserini/2cr/msmarco_html_v1_passage.template
pyserini/2cr/msmarco_html_v2_doc.template
pyserini/2cr/msmarco_html_v2_passage.template
pyserini/2cr/naturalquestion.yaml
pyserini/2cr/odqa.py
pyserini/2cr/odqa_html.template
pyserini/2cr/odqa_html_table.template
pyserini/2cr/odqa_html_table_row.template
pyserini/2cr/odqa_html_table_row_gar-rrf.template
pyserini/2cr/odqa_html_table_row_rrf.template
pyserini/2cr/triviaqa.yaml
pyserini/analysis/__init__.py
pyserini/analysis/_base.py
pyserini/collection/__init__.py
pyserini/collection/_base.py
mseep_pyserini-1.2.4.dist-info/METADATA
mseep_pyserini-1.2.4.dist-info/WHEEL
mseep_pyserini-1.2.4.dist-info/top_level.txt
mseep_pyserini-1.2.4.dist-info/RECORD
